my_package_alexander_pershin_2/__init__.py
my_package_alexander_pershin_2/main.py
my_package_alexander_pershin_2-0.1.2.dist-info/METADATA
my_package_alexander_pershin_2-0.1.2.dist-info/WHEEL
my_package_alexander_pershin_2-0.1.2.dist-info/top_level.txt
my_package_alexander_pershin_2-0.1.2.dist-info/RECORD
