Metadata-Version: 2.4
Name: my-package-alexander-pershin-2
Version: 0.1.2
Summary: My sample project
Author-email: Alexander <alexander@email.com>
License: MIT
Requires-Python: >=3.12
